zsh2xonsh/__init__.py
zsh2xonsh/__main__.py
zsh2xonsh/ast.py
zsh2xonsh/parser.py
zsh2xonsh/runtime.py
zsh2xonsh/translate.py
zsh2xonsh-0.1.0b1.dist-info/LICENSE.md
zsh2xonsh-0.1.0b1.dist-info/METADATA
zsh2xonsh-0.1.0b1.dist-info/WHEEL
zsh2xonsh-0.1.0b1.dist-info/entry_points.txt
zsh2xonsh-0.1.0b1.dist-info/top_level.txt
zsh2xonsh-0.1.0b1.dist-info/RECORD
