Metadata-Version: 2.1
Name: zsh2xonsh
Version: 0.1.0b1
Summary: A highly-compatible translator from zsh -> xonsh
Home-page: https://github.com/Techcable/zsh2xonsh
Maintainer: Techcable
License: MIT
Keywords: shell xonsh zsh cli translate compat
Platform: UNKNOWN
Classifier: Development Status :: 3 - Alpha
Classifier: Environment :: Console
Classifier: Operating System :: OS Independent
Classifier: License :: OSI Approved :: MIT License
Classifier: Topic :: System :: Shells
Classifier: Topic :: System :: System Shells
Requires-Python: >=3.8
License-File: LICENSE.md
Requires-Dist: click
